Metadata-Version: 2.1
Name: azure-cli-appservice
Version: 0.2.21
Summary: Microsoft Azure Command-Line Tools AppService Command Module
Home-page: https://github.com/Azure/azure-cli
Author: Microsoft Corporation
Author-email: azpycli@microsoft.com
License: MIT
Platform: UNKNOWN
Classifier: Development Status :: 4 - Beta
Classifier: Intended Audience :: Developers
Classifier: Intended Audience :: System Administrators
Classifier: Programming Language :: Python
Classifier: Programming Language :: Python :: 2
Classifier: Programming Language :: Python :: 2.7
Classifier: Programming Language :: Python :: 3
Classifier: Programming Language :: Python :: 3.4
Classifier: Programming Language :: Python :: 3.5
Classifier: Programming Language :: Python :: 3.6
Classifier: License :: OSI Approved :: MIT License
Requires-Dist: azure-cli-core
Requires-Dist: azure-functions-devops-build (==0.0.22)
Requires-Dist: azure-mgmt-web (==0.42.0)
Requires-Dist: azure-mgmt-storage (==3.3.0)
Requires-Dist: azure-mgmt-containerregistry (==2.8.0)
Requires-Dist: azure-mgmt-applicationinsights (==0.1.1)
Requires-Dist: urllib3[secure] (>=1.18)
Requires-Dist: xmltodict
Requires-Dist: fabric (>=2.4)
Requires-Dist: cryptography
Requires-Dist: pyOpenSSL
Requires-Dist: six
Requires-Dist: vsts-cd-manager (<1.1.0)
Requires-Dist: azure-cli-command-modules-nspkg (>=2.0.0)
